platform_observability/__init__.py
platform_observability/endpoint.py
platform_observability/extension.py
platform_observability/instruments/__init__.py
platform_observability/instruments/aggregate.py
platform_observability/instruments/core.py
platform_observability/instruments/sns.py
platform_observability/instruments/sqs.py
platform_observability/tracing/__init__.py
platform_observability/tracing/lambda_.py
platform_observability/tracing/lambda_sqs.py
platform_observability/tracing/logging.py
localstack_extension_platform_observability-0.0.3.dist-info/METADATA
localstack_extension_platform_observability-0.0.3.dist-info/WHEEL
localstack_extension_platform_observability-0.0.3.dist-info/entry_points.txt
localstack_extension_platform_observability-0.0.3.dist-info/top_level.txt
localstack_extension_platform_observability-0.0.3.dist-info/RECORD
