Metadata-Version: 2.1
Name: localstack-extension-platform-observability
Version: 0.0.3
Summary: LocalStack Extension: LocalStack Extension: Platform observability
Home-page: https://github.com/localstack/localstack-extension-platform-observability
Author: LocalStack Contributors
Author-email: info@localstack.cloud
Provides-Extra: dev
Requires-Dist: localstack-core >=3.5 ; extra == 'dev'
